thousandeyes_sdk/endpoint_agents/__init__.py
thousandeyes_sdk/endpoint_agents/py.typed
thousandeyes_sdk/endpoint_agents/api/__init__.py
thousandeyes_sdk/endpoint_agents/api/endpoint_agents_api.py
thousandeyes_sdk/endpoint_agents/api/endpoint_agents_transfer_api.py
thousandeyes_sdk/endpoint_agents/models/__init__.py
thousandeyes_sdk/endpoint_agents/models/address_profile.py
thousandeyes_sdk/endpoint_agents/models/address_type.py
thousandeyes_sdk/endpoint_agents/models/agent_license_type.py
thousandeyes_sdk/endpoint_agents/models/agent_search_filters.py
thousandeyes_sdk/endpoint_agents/models/agent_search_request.py
thousandeyes_sdk/endpoint_agents/models/agent_search_sort.py
thousandeyes_sdk/endpoint_agents/models/agent_search_sort_key.py
thousandeyes_sdk/endpoint_agents/models/agent_threshold_filter.py
thousandeyes_sdk/endpoint_agents/models/agent_threshold_filters.py
thousandeyes_sdk/endpoint_agents/models/agent_transfer.py
thousandeyes_sdk/endpoint_agents/models/agent_transfer_request.py
thousandeyes_sdk/endpoint_agents/models/agent_transfer_status.py
thousandeyes_sdk/endpoint_agents/models/browser_type.py
thousandeyes_sdk/endpoint_agents/models/bulk_agent_transfer_request.py
thousandeyes_sdk/endpoint_agents/models/bulk_agent_transfer_response.py
thousandeyes_sdk/endpoint_agents/models/conditional_operator.py
thousandeyes_sdk/endpoint_agents/models/connection_string.py
thousandeyes_sdk/endpoint_agents/models/endpoint_agent.py
thousandeyes_sdk/endpoint_agents/models/endpoint_agent_ethernet_profile.py
thousandeyes_sdk/endpoint_agents/models/endpoint_agent_location.py
thousandeyes_sdk/endpoint_agents/models/endpoint_agent_update.py
thousandeyes_sdk/endpoint_agents/models/endpoint_agents.py
thousandeyes_sdk/endpoint_agents/models/endpoint_asn_details.py
thousandeyes_sdk/endpoint_agents/models/endpoint_browser_extension.py
thousandeyes_sdk/endpoint_agents/models/endpoint_client.py
thousandeyes_sdk/endpoint_agents/models/endpoint_user_profile.py
thousandeyes_sdk_endpoint_agents-2.23.0.dist-info/licenses/LICENSE
thousandeyes_sdk_endpoint_agents-2.23.0.dist-info/licenses/NOTICE
thousandeyes_sdk_endpoint_agents-2.23.0.dist-info/METADATA
thousandeyes_sdk_endpoint_agents-2.23.0.dist-info/WHEEL
thousandeyes_sdk_endpoint_agents-2.23.0.dist-info/top_level.txt
thousandeyes_sdk_endpoint_agents-2.23.0.dist-info/RECORD
